anonfile/__init__.py
anonfile/anonfile.py
anonfile/exceptions.py
anonfile/utils.py
anonfile_uploader-0.1.5.dist-info/LICENSE
anonfile_uploader-0.1.5.dist-info/METADATA
anonfile_uploader-0.1.5.dist-info/WHEEL
anonfile_uploader-0.1.5.dist-info/top_level.txt
anonfile_uploader-0.1.5.dist-info/RECORD
